{"data":{"github":{"viewer":{"repositories":{"nodes":[{"owner":{"__typename":"GitHub_User","login":"SMCRunner88"},"name":"scotts-portfolio","url":"https://github.com/SMCRunner88/scotts-portfolio","description":"Repo for github portfolio using gatsby","stargazers":{"totalCount":0},"forkCount":0},{"owner":{"__typename":"GitHub_User","login":"SMCRunner88"},"name":"notey-notes","url":"https://github.com/SMCRunner88/notey-notes","description":null,"stargazers":{"totalCount":0},"forkCount":0},{"owner":{"__typename":"GitHub_User","login":"SMCRunner88"},"name":"coding-train-data-apis","url":"https://github.com/SMCRunner88/coding-train-data-apis","description":"Youtuber coding apis lessons with exercises done on your (my) own.","stargazers":{"totalCount":0},"forkCount":0},{"owner":{"__typename":"GitHub_User","login":"SMCRunner88"},"name":"JavaScript30","url":"https://github.com/SMCRunner88/JavaScript30","description":"30 Day Vanilla JS Challenge","stargazers":{"totalCount":0},"forkCount":0},{"owner":{"__typename":"GitHub_User","login":"SMCRunner88"},"name":"Modern-JavaScript","url":"https://github.com/SMCRunner88/Modern-JavaScript","description":"Code for TylerMcGinnis.com's \"Modern JavaScript\" course","stargazers":{"totalCount":0},"forkCount":0},{"owner":{"__typename":"GitHub_User","login":"SMCRunner88"},"name":"vue-mastery","url":"https://github.com/SMCRunner88/vue-mastery","description":null,"stargazers":{"totalCount":0},"forkCount":0},{"owner":{"__typename":"GitHub_User","login":"SMCRunner88"},"name":"HogwartsNewsletter","url":"https://github.com/SMCRunner88/HogwartsNewsletter","description":"A newsletter from Hogwarts School of Witchcraft and Wizardry","stargazers":{"totalCount":0},"forkCount":0},{"owner":{"__typename":"GitHub_User","login":"SMCRunner88"},"name":"framer-bridge-starter-kit","url":"https://github.com/SMCRunner88/framer-bridge-starter-kit","description":"Start your design system in Framer X.","stargazers":{"totalCount":0},"forkCount":0},{"owner":{"__typename":"GitHub_User","login":"lji543"},"name":"budgetAppGA","url":"https://github.com/lji543/budgetAppGA","description":null,"stargazers":{"totalCount":1},"forkCount":0}]}}}}}